<?xml version="1.0" encoding="UTF-8"?>
<document filename="POD_0792.jpg">
    <table>
        <Coords points="148,340 909,340 909,1063 148,1063"/>
        <cell id="0" neighbors="1:R">
            <Coords points="297,352 353,352 353,371 297,371"/>
        </cell>
        <cell id="1" neighbors="0:L 2:R 17:B">
            <Coords points="375,351 441,351 441,371 375,371"/>
        </cell>
        <cell id="2" neighbors="1:L 3:R 15:B">
            <Coords points="462,353 529,353 529,371 462,371"/>
        </cell>
        <cell id="3" neighbors="2:L 4:R 13:B">
            <Coords points="551,353 617,353 617,370 551,370"/>
        </cell>
        <cell id="4" neighbors="3:L 5:R 11:B">
            <Coords points="644,352 712,352 712,370 644,370"/>
        </cell>
        <cell id="5" neighbors="4:L 6:R 9:B">
            <Coords points="739,352 802,352 802,370 739,370"/>
        </cell>
        <cell id="6" neighbors="5:L 7:B">
            <Coords points="832,352 895,352 895,370 832,370"/>
        </cell>
        <cell id="7" neighbors="6:T 8:B 9:L">
            <Coords points="878,384 906,384 906,402 878,402"/>
        </cell>
        <cell id="8" neighbors="7:T 10:L 136:B">
            <Coords points="868,415 905,415 905,434 868,434"/>
        </cell>
        <cell id="9" neighbors="5:T 7:R 10:B 11:L">
            <Coords points="786,383 815,383 815,402 786,402"/>
        </cell>
        <cell id="10" neighbors="8:R 9:T 12:L 135:B">
            <Coords points="786,416 815,416 815,435 786,435"/>
        </cell>
        <cell id="11" neighbors="4:T 9:R 12:B 13:L">
            <Coords points="692,384 722,384 722,403 692,403"/>
        </cell>
        <cell id="12" neighbors="10:R 11:T 14:L 128:B">
            <Coords points="694,416 721,416 721,435 694,435"/>
        </cell>
        <cell id="13" neighbors="3:T 11:R 14:B 15:L">
            <Coords points="600,384 628,384 628,403 600,403"/>
        </cell>
        <cell id="14" neighbors="12:R 13:T 16:L 125:B">
            <Coords points="591,416 627,416 627,434 591,434"/>
        </cell>
        <cell id="15" neighbors="2:T 13:R 16:B 17:L">
            <Coords points="498,385 534,385 534,402 498,402"/>
        </cell>
        <cell id="16" neighbors="14:R 15:T 18:L 122:B">
            <Coords points="495,416 533,416 533,434 495,434"/>
        </cell>
        <cell id="17" neighbors="1:T 15:R 18:B 19:L">
            <Coords points="410,384 448,384 448,402 410,402"/>
        </cell>
        <cell id="18" neighbors="16:R 17:T 20:L 121:B">
            <Coords points="410,416 448,416 448,434 410,434"/>
        </cell>
        <cell id="19" neighbors="17:R 20:B">
            <Coords points="155,384 232,384 232,403 155,403"/>
        </cell>
        <cell id="20" neighbors="18:R 19:T 21:B">
            <Coords points="155,416 313,416 313,438 155,438"/>
        </cell>
        <cell id="21" neighbors="20:T 22:B">
            <Coords points="155,448 299,448 299,470 155,470"/>
        </cell>
        <cell id="22" neighbors="21:T 23:B 120:R">
            <Coords points="181,479 229,479 229,497 181,497"/>
        </cell>
        <cell id="23" neighbors="22:T 24:B 43:R">
            <Coords points="181,511 219,511 219,528 181,528"/>
        </cell>
        <cell id="24" neighbors="23:T 25:B 28:R">
            <Coords points="181,542 201,542 201,559 181,559"/>
        </cell>
        <cell id="25" neighbors="24:T 26:B">
            <Coords points="155,573 246,573 246,591 155,591"/>
        </cell>
        <cell id="26" neighbors="25:T 27:R 29:B">
            <Coords points="181,604 229,604 229,622 181,622"/>
        </cell>
        <cell id="27" neighbors="26:L 28:T 37:B 46:R">
            <Coords points="311,605 349,605 349,622 311,622"/>
        </cell>
        <cell id="28" neighbors="24:L 27:B 43:T 45:R">
            <Coords points="317,542 348,542 348,560 317,560"/>
        </cell>
        <cell id="29" neighbors="26:T 30:B 37:R">
            <Coords points="180,636 221,636 221,653 180,653"/>
        </cell>
        <cell id="30" neighbors="29:T 31:B 36:R">
            <Coords points="181,667 201,667 201,684 181,684"/>
        </cell>
        <cell id="31" neighbors="30:T 32:B">
            <Coords points="155,697 259,697 259,719 155,719"/>
        </cell>
        <cell id="32" neighbors="31:T 33:B 38:R">
            <Coords points="180,729 229,729 229,748 180,748"/>
        </cell>
        <cell id="33" neighbors="32:T 34:B 39:R">
            <Coords points="180,760 220,760 220,778 180,778"/>
        </cell>
        <cell id="34" neighbors="33:T 35:B 40:R">
            <Coords points="180,790 202,790 202,809 180,809"/>
        </cell>
        <cell id="35" neighbors="34:T 59:B">
            <Coords points="154,821 231,821 231,845 154,845"/>
        </cell>
        <cell id="36" neighbors="30:L 37:T 38:B 48:R">
            <Coords points="311,666 349,666 349,684 311,684"/>
        </cell>
        <cell id="37" neighbors="27:T 29:L 36:B 47:R">
            <Coords points="311,635 350,635 350,653 311,653"/>
        </cell>
        <cell id="38" neighbors="32:L 36:T 39:B 41:R">
            <Coords points="310,729 350,729 350,747 310,747"/>
        </cell>
        <cell id="39" neighbors="33:L 38:T 40:B 42:R">
            <Coords points="312,760 349,760 349,778 312,778"/>
        </cell>
        <cell id="40" neighbors="34:L 39:T 49:R 71:B">
            <Coords points="311,791 350,791 350,809 311,809"/>
        </cell>
        <cell id="41" neighbors="38:L 42:B 48:T 50:R">
            <Coords points="389,729 435,729 435,747 389,747"/>
        </cell>
        <cell id="42" neighbors="39:L 41:T 49:B 51:R">
            <Coords points="389,760 435,760 435,778 389,778"/>
        </cell>
        <cell id="43" neighbors="23:L 28:B 44:R 120:T">
            <Coords points="316,509 348,509 348,528 316,528"/>
        </cell>
        <cell id="44" neighbors="43:L 45:B 121:T 123:R">
            <Coords points="397,510 434,510 434,528 397,528"/>
        </cell>
        <cell id="45" neighbors="28:L 44:T 46:B 124:R">
            <Coords points="396,541 435,541 435,560 396,560"/>
        </cell>
        <cell id="46" neighbors="27:L 45:T 47:B 53:R">
            <Coords points="389,604 434,604 434,622 389,622"/>
        </cell>
        <cell id="47" neighbors="37:L 46:T 48:B 54:R">
            <Coords points="389,636 435,636 435,653 389,653"/>
        </cell>
        <cell id="48" neighbors="36:L 41:B 47:T 55:R">
            <Coords points="389,666 435,666 435,685 389,685"/>
        </cell>
        <cell id="49" neighbors="40:L 42:T 52:R 72:B">
            <Coords points="389,791 435,791 435,809 389,809"/>
        </cell>
        <cell id="50" neighbors="41:L 51:B 55:T 117:R">
            <Coords points="484,729 522,729 522,747 484,747"/>
        </cell>
        <cell id="51" neighbors="42:L 50:T 52:B 118:R">
            <Coords points="476,761 519,761 519,778 476,778"/>
        </cell>
        <cell id="52" neighbors="49:L 51:T 81:B 119:R">
            <Coords points="475,791 522,791 522,809 475,809"/>
        </cell>
        <cell id="53" neighbors="46:L 54:B 56:R 124:T">
            <Coords points="475,605 521,605 521,622 475,622"/>
        </cell>
        <cell id="54" neighbors="47:L 53:T 55:B 57:R">
            <Coords points="475,635 521,635 521,653 475,653"/>
        </cell>
        <cell id="55" neighbors="48:L 50:B 54:T 58:R">
            <Coords points="475,666 521,666 521,684 475,684"/>
        </cell>
        <cell id="56" neighbors="53:L 57:B 127:T 131:R">
            <Coords points="579,604 614,604 614,622 579,622"/>
        </cell>
        <cell id="57" neighbors="54:L 56:T 58:B 141:R">
            <Coords points="568,635 615,635 615,654 568,654"/>
        </cell>
        <cell id="58" neighbors="55:L 57:T 117:B 142:R">
            <Coords points="567,666 615,666 615,684 567,684"/>
        </cell>
        <cell id="59" neighbors="35:T 60:B 71:R">
            <Coords points="180,854 229,854 229,872 180,872"/>
        </cell>
        <cell id="60" neighbors="59:T 61:B 70:R">
            <Coords points="181,886 220,886 220,903 181,903"/>
        </cell>
        <cell id="61" neighbors="60:T 62:B 69:R">
            <Coords points="182,916 200,916 200,933 182,933"/>
        </cell>
        <cell id="62" neighbors="61:T 63:B">
            <Coords points="155,947 262,947 262,969 155,969"/>
        </cell>
        <cell id="63" neighbors="62:T 64:B 66:R">
            <Coords points="181,979 228,979 228,996 181,996"/>
        </cell>
        <cell id="64" neighbors="63:T 65:B 67:R">
            <Coords points="180,1010 220,1010 220,1028 180,1028"/>
        </cell>
        <cell id="65" neighbors="64:T 68:R">
            <Coords points="181,1041 201,1041 201,1059 181,1059"/>
        </cell>
        <cell id="66" neighbors="63:L 67:B 69:T 75:R">
            <Coords points="321,979 348,979 348,996 321,996"/>
        </cell>
        <cell id="67" neighbors="64:L 66:T 68:B 76:R">
            <Coords points="311,1010 347,1010 347,1028 311,1028"/>
        </cell>
        <cell id="68" neighbors="65:L 67:T 77:R">
            <Coords points="312,1041 349,1041 349,1059 312,1059"/>
        </cell>
        <cell id="69" neighbors="61:L 66:B 70:T 74:R">
            <Coords points="311,916 349,916 349,934 311,934"/>
        </cell>
        <cell id="70" neighbors="60:L 69:B 71:T 73:R">
            <Coords points="311,885 349,885 349,903 311,903"/>
        </cell>
        <cell id="71" neighbors="40:T 59:L 70:B 72:R">
            <Coords points="312,854 349,854 349,872 312,872"/>
        </cell>
        <cell id="72" neighbors="49:T 71:L 73:B 81:R">
            <Coords points="389,854 435,854 435,872 389,872"/>
        </cell>
        <cell id="73" neighbors="70:L 72:T 74:B 82:R">
            <Coords points="389,885 435,885 435,903 389,903"/>
        </cell>
        <cell id="74" neighbors="69:L 73:T 75:B 83:R">
            <Coords points="389,915 435,915 435,934 389,934"/>
        </cell>
        <cell id="75" neighbors="66:L 74:T 76:B 78:R">
            <Coords points="388,979 435,979 435,998 388,998"/>
        </cell>
        <cell id="76" neighbors="67:L 75:T 77:B 79:R">
            <Coords points="389,1009 435,1009 435,1029 389,1029"/>
        </cell>
        <cell id="77" neighbors="68:L 76:T 80:R">
            <Coords points="389,1041 435,1041 435,1059 389,1059"/>
        </cell>
        <cell id="78" neighbors="75:L 79:B 83:T 87:R">
            <Coords points="475,979 521,979 521,997 475,997"/>
        </cell>
        <cell id="79" neighbors="76:L 78:T 80:B 88:R">
            <Coords points="475,1010 521,1010 521,1028 475,1028"/>
        </cell>
        <cell id="80" neighbors="77:L 79:T 89:R">
            <Coords points="476,1041 521,1041 521,1058 476,1058"/>
        </cell>
        <cell id="81" neighbors="52:T 72:L 82:B 84:R">
            <Coords points="474,854 522,854 522,872 474,872"/>
        </cell>
        <cell id="82" neighbors="73:L 81:T 83:B 85:R">
            <Coords points="474,886 521,886 521,903 474,903"/>
        </cell>
        <cell id="83" neighbors="74:L 78:B 82:T 86:R">
            <Coords points="474,916 523,916 523,934 474,934"/>
        </cell>
        <cell id="84" neighbors="81:L 85:B 93:R 119:T">
            <Coords points="567,853 614,853 614,872 567,872"/>
        </cell>
        <cell id="85" neighbors="82:L 84:T 86:B 94:R">
            <Coords points="567,886 615,886 615,904 567,904"/>
        </cell>
        <cell id="86" neighbors="83:L 85:T 87:B 95:R">
            <Coords points="568,916 614,916 614,935 568,935"/>
        </cell>
        <cell id="87" neighbors="78:L 86:T 88:B 90:R">
            <Coords points="568,978 614,978 614,999 568,999"/>
        </cell>
        <cell id="88" neighbors="79:L 87:T 89:B 91:R">
            <Coords points="568,1010 614,1010 614,1029 568,1029"/>
        </cell>
        <cell id="89" neighbors="80:L 88:T 92:R">
            <Coords points="567,1040 614,1040 614,1059 567,1059"/>
        </cell>
        <cell id="90" neighbors="87:L 91:B 95:T 99:R">
            <Coords points="663,979 708,979 708,997 663,997"/>
        </cell>
        <cell id="91" neighbors="88:L 90:T 92:B 100:R">
            <Coords points="663,1009 707,1009 707,1029 663,1029"/>
        </cell>
        <cell id="92" neighbors="89:L 91:T 101:R">
            <Coords points="663,1041 707,1041 707,1059 663,1059"/>
        </cell>
        <cell id="93" neighbors="84:L 94:B 96:R 116:T">
            <Coords points="671,853 709,853 709,872 671,872"/>
        </cell>
        <cell id="94" neighbors="85:L 93:T 95:B 97:R">
            <Coords points="662,886 709,886 709,904 662,904"/>
        </cell>
        <cell id="95" neighbors="86:L 90:B 94:T 98:R">
            <Coords points="662,915 707,915 707,935 662,935"/>
        </cell>
        <cell id="96" neighbors="93:L 97:B 107:R 113:T">
            <Coords points="755,853 801,853 801,872 755,872"/>
        </cell>
        <cell id="97" neighbors="94:L 96:T 98:B 106:R">
            <Coords points="766,884 801,884 801,903 766,903"/>
        </cell>
        <cell id="98" neighbors="95:L 97:T 99:B 105:R">
            <Coords points="766,915 801,915 801,935 766,935"/>
        </cell>
        <cell id="99" neighbors="90:L 98:T 100:B 104:R">
            <Coords points="755,979 800,979 800,997 755,997"/>
        </cell>
        <cell id="100" neighbors="91:L 99:T 101:B 103:R">
            <Coords points="766,1010 801,1010 801,1028 766,1028"/>
        </cell>
        <cell id="101" neighbors="92:L 100:T 102:R">
            <Coords points="766,1041 801,1041 801,1059 766,1059"/>
        </cell>
        <cell id="102" neighbors="101:L 103:T">
            <Coords points="848,1041 890,1041 890,1059 848,1059"/>
        </cell>
        <cell id="103" neighbors="100:L 102:B 104:T">
            <Coords points="847,1011 891,1011 891,1029 847,1029"/>
        </cell>
        <cell id="104" neighbors="99:L 103:B 105:T">
            <Coords points="857,980 892,980 892,997 857,997"/>
        </cell>
        <cell id="105" neighbors="98:L 104:B 106:T">
            <Coords points="846,917 890,917 890,934 846,934"/>
        </cell>
        <cell id="106" neighbors="97:L 105:B 107:T">
            <Coords points="848,885 892,885 892,903 848,903"/>
        </cell>
        <cell id="107" neighbors="96:L 106:B 108:T">
            <Coords points="857,855 891,855 891,872 857,872"/>
        </cell>
        <cell id="108" neighbors="107:B 109:T 113:L">
            <Coords points="857,792 893,792 893,809 857,809"/>
        </cell>
        <cell id="109" neighbors="108:B 110:T 112:L">
            <Coords points="858,760 892,760 892,778 858,778"/>
        </cell>
        <cell id="110" neighbors="109:B 111:L 145:T">
            <Coords points="867,730 892,730 892,747 867,747"/>
        </cell>
        <cell id="111" neighbors="110:R 112:B 114:L 140:T">
            <Coords points="773,730 801,730 801,747 773,747"/>
        </cell>
        <cell id="112" neighbors="109:R 111:T 113:B 115:L">
            <Coords points="766,761 799,761 799,778 766,778"/>
        </cell>
        <cell id="113" neighbors="96:B 108:R 112:T 116:L">
            <Coords points="766,792 800,792 800,809 766,809"/>
        </cell>
        <cell id="114" neighbors="111:R 115:B 117:L 142:T">
            <Coords points="673,730 708,730 708,747 673,747"/>
        </cell>
        <cell id="115" neighbors="112:R 114:T 116:B 118:L">
            <Coords points="673,761 707,761 707,778 673,778"/>
        </cell>
        <cell id="116" neighbors="93:B 113:R 115:T 119:L">
            <Coords points="672,791 707,791 707,809 672,809"/>
        </cell>
        <cell id="117" neighbors="50:L 58:T 114:R 118:B">
            <Coords points="588,729 615,729 615,747 588,747"/>
        </cell>
        <cell id="118" neighbors="51:L 115:R 117:T 119:B">
            <Coords points="579,761 613,761 613,779 579,779"/>
        </cell>
        <cell id="119" neighbors="52:L 84:B 116:R 118:T">
            <Coords points="579,791 614,791 614,810 579,810"/>
        </cell>
        <cell id="120" neighbors="22:L 43:B 121:R">
            <Coords points="302,479 349,479 349,496 302,496"/>
        </cell>
        <cell id="121" neighbors="18:T 44:B 120:L 122:R">
            <Coords points="407,480 435,480 435,497 407,497"/>
        </cell>
        <cell id="122" neighbors="16:T 121:L 123:B 125:R">
            <Coords points="494,479 520,479 520,498 494,498"/>
        </cell>
        <cell id="123" neighbors="44:L 122:T 124:B 126:R">
            <Coords points="482,510 522,510 522,529 482,529"/>
        </cell>
        <cell id="124" neighbors="45:L 53:B 123:T 127:R">
            <Coords points="484,543 522,543 522,561 484,561"/>
        </cell>
        <cell id="125" neighbors="14:T 122:L 126:B 128:R">
            <Coords points="587,480 615,480 615,498 587,498"/>
        </cell>
        <cell id="126" neighbors="123:L 125:T 127:B 129:R">
            <Coords points="577,511 613,511 613,528 577,528"/>
        </cell>
        <cell id="127" neighbors="56:B 124:L 126:T 130:R">
            <Coords points="586,543 615,543 615,561 586,561"/>
        </cell>
        <cell id="128" neighbors="12:T 125:L 129:B 135:R">
            <Coords points="679,480 708,480 708,499 679,499"/>
        </cell>
        <cell id="129" neighbors="126:L 128:T 130:B 134:R">
            <Coords points="680,510 709,510 709,528 680,528"/>
        </cell>
        <cell id="130" neighbors="127:L 129:T 131:B 133:R">
            <Coords points="679,542 707,542 707,561 679,561"/>
        </cell>
        <cell id="131" neighbors="56:L 130:T 132:R 141:B">
            <Coords points="672,605 709,605 709,623 672,623"/>
        </cell>
        <cell id="132" neighbors="131:L 133:T 139:B 143:R">
            <Coords points="766,605 802,605 802,622 766,622"/>
        </cell>
        <cell id="133" neighbors="130:L 132:B 134:T 138:R">
            <Coords points="774,543 801,543 801,560 774,560"/>
        </cell>
        <cell id="134" neighbors="129:L 133:B 135:T 137:R">
            <Coords points="773,510 802,510 802,528 773,528"/>
        </cell>
        <cell id="135" neighbors="10:T 128:L 134:B 136:R">
            <Coords points="775,479 800,479 800,497 775,497"/>
        </cell>
        <cell id="136" neighbors="8:T 135:L 137:B">
            <Coords points="857,479 892,479 892,497 857,497"/>
        </cell>
        <cell id="137" neighbors="134:L 136:T 138:B">
            <Coords points="855,510 892,510 892,529 855,529"/>
        </cell>
        <cell id="138" neighbors="133:L 137:T 143:B">
            <Coords points="865,541 892,541 892,561 865,561"/>
        </cell>
        <cell id="139" neighbors="132:T 140:B 141:L 144:R">
            <Coords points="773,636 801,636 801,653 773,653"/>
        </cell>
        <cell id="140" neighbors="111:B 139:T 142:L 145:R">
            <Coords points="767,667 801,667 801,684 767,684"/>
        </cell>
        <cell id="141" neighbors="57:L 131:T 139:R 142:B">
            <Coords points="672,635 708,635 708,653 672,653"/>
        </cell>
        <cell id="142" neighbors="58:L 114:B 140:R 141:T">
            <Coords points="672,666 707,666 707,684 672,684"/>
        </cell>
        <cell id="143" neighbors="132:L 138:T 144:B">
            <Coords points="856,605 891,605 891,622 856,622"/>
        </cell>
        <cell id="144" neighbors="139:L 143:T 145:B">
            <Coords points="847,634 892,634 892,653 847,653"/>
        </cell>
        <cell id="145" neighbors="110:B 140:L 144:T">
            <Coords points="848,666 892,666 892,684 848,684"/>
        </cell>
    </table>
</document>
